traceback_with_variables/__init__.py
traceback_with_variables/a.py
traceback_with_variables/activate_by_import.py
traceback_with_variables/activate_in_ipython_by_import.py
traceback_with_variables/activate_in_python_by_import.py
traceback_with_variables/color.py
traceback_with_variables/core.py
traceback_with_variables/default_global_hooks.py
traceback_with_variables/fast_capped_str_casts.py
traceback_with_variables/global_hooks.py
traceback_with_variables/main.py
traceback_with_variables/module_alias.py
traceback_with_variables/print.py
traceback_with_variables/tb_alias.py
traceback_with_variables-2.2.1.dist-info/LICENSE
traceback_with_variables-2.2.1.dist-info/METADATA
traceback_with_variables-2.2.1.dist-info/WHEEL
traceback_with_variables-2.2.1.dist-info/entry_points.txt
traceback_with_variables-2.2.1.dist-info/top_level.txt
traceback_with_variables-2.2.1.dist-info/RECORD
