Metadata-Version: 2.1
Name: traceback_with_variables
Version: 2.2.1
Summary: Adds variables to python traceback. Simple, lightweight, controllable. Debug reasons of exceptions by logging or pretty printing colorful variable contexts for each frame in a stacktrace, showing every value. Dump locals environments after errors to console, files, and loggers. Works with Jupyter and IPython.
Home-page: https://github.com/andy-landy/traceback_with_variables
Author: Andrey Lyashko
Author-email: andydashlandy@gmail.com
License: UNKNOWN
Keywords: python,traceback,locals,logging,debugging,print,variables,python3,stacktrace,arguments,errors,error-handling,dump,exception-handling,exceptions,pretty,pretty-print,frame,simple,colors,jupyter,jupyter-notebook,ipython,customize
Platform: UNKNOWN
Classifier: Programming Language :: Python :: 3
Classifier: License :: OSI Approved :: MIT License
Classifier: Operating System :: OS Independent
Classifier: Intended Audience :: Developers
Classifier: Topic :: Software Development :: Debuggers
Classifier: Topic :: Software Development :: Libraries
Requires-Python: >=3.7
Provides-Extra: test
